rascore/.DS_Store
rascore/.streamlit/config.toml
rascore/rascore_cli.py
rascore/rascore_gui.py
rascore/util/.DS_Store
rascore/util/PDBrenum/.DS_Store
rascore/util/PDBrenum/PDBrenum.py
rascore/util/PDBrenum/src/.DS_Store
rascore/util/PDBrenum/src/download/catalogdownloader.py
rascore/util/PDBrenum/src/download/compressor.py
rascore/util/PDBrenum/src/download/deletefiles.py
rascore/util/PDBrenum/src/download/downloadwithThreadPool.py
rascore/util/PDBrenum/src/download/inputtextfileparser.py
rascore/util/PDBrenum/src/download/latestcatreader.py
rascore/util/PDBrenum/src/download/lefttodownload.py
rascore/util/PDBrenum/src/download/lefttorenumber.py
rascore/util/PDBrenum/src/download/longusagemessage.py
rascore/util/PDBrenum/src/download/lookfilesinside.py
rascore/util/PDBrenum/src/download/modules.py
rascore/util/PDBrenum/src/download/shortusagemessage.py
rascore/util/PDBrenum/src/download/supremedownloader.py
rascore/util/PDBrenum/src/renum/.DS_Store
rascore/util/PDBrenum/src/renum/PDB/new_PDB.py
rascore/util/PDBrenum/src/renum/mmCIF/ProcessPool_run_renum_mmCIF.py
rascore/util/PDBrenum/src/renum/mmCIF/new_mmCIF.py
rascore/util/PDBrenum/src/renum/shared/SIFTS_tree_parser.py
rascore/util/PDBrenum/src/renum/shared/handling_chain_numbering_clashes.py
rascore/util/PDBrenum/src/renum/shared/renumbered_count_in_chains.py
rascore/util/PDBrenum/src/renum/shared/try_SIFTS_tree_parser.py
rascore/util/PDBrenum/src/renum/shared/write_log.py
rascore/util/constants/.DS_Store
rascore/util/constants/conf.py
rascore/util/constants/dimer.py
rascore/util/constants/gene.py
rascore/util/constants/mut.py
rascore/util/constants/nuc.py
rascore/util/constants/pharm.py
rascore/util/constants/pml.py
rascore/util/constants/pocket.py
rascore/util/constants/prot.py
rascore/util/data/.DS_Store
rascore/util/data/dihedral.json
rascore/util/data/entry.tsv
rascore/util/data/interface.tsv
rascore/util/data/pocket.tsv
rascore/util/data/rascore_abstract.png
rascore/util/data/rascore_cluster/.DS_Store
rascore-1.0.7.dist-info/entry_points.txt
rascore-1.0.7.dist-info/LICENSE
rascore-1.0.7.dist-info/WHEEL
rascore-1.0.7.dist-info/METADATA
rascore-1.0.7.dist-info/RECORD
