Metadata-Version: 2.1
Name: rascore
Version: 1.0.7
Summary: A tool for analyzing RAS protein structures
License: Apache-2.0
Author: mitch-parker
Author-email: mip34@drexel.edu
Requires-Python: >=3.8,<3.9
Classifier: License :: OSI Approved :: Apache Software License
Classifier: Programming Language :: Python :: 3
Classifier: Programming Language :: Python :: 3.8
Requires-Dist: Bio (==1.3.3)
Requires-Dist: Pillow (==9.0.1)
Requires-Dist: lxml (==4.6.5)
Requires-Dist: matplotlib (==3.3.4)
Requires-Dist: matplotlib_venn (==0.11.6)
Requires-Dist: numpy (==1.21)
Requires-Dist: pandas (==1.3.5)
Requires-Dist: pendulum (==2.1.2)
Requires-Dist: py3Dmol (==2.0.0.post2)
Requires-Dist: pyfiglet (==0.8.post1)
Requires-Dist: rdkit_pypi (==2021.9.5.1)
Requires-Dist: requests (==2.25.1)
Requires-Dist: scipy (==1.6.2)
Requires-Dist: seaborn (==0.11.1)
Requires-Dist: statannot (==0.2.3)
Requires-Dist: statsmodels (==0.13.1)
Requires-Dist: stmol (==0.0.7)
Requires-Dist: streamlit (==1.8.1)
Requires-Dist: tqdm (==4.59.0)
